{"dependencies":[{"name":"./convert","loc":{"line":1,"column":22}},{"name":"../includes","loc":{"line":2,"column":39}},{"name":"./placeholder","loc":{"line":4,"column":27}}],"generated":{"js":"var convert = require('./convert'),\n    func = convert('includes', require('../includes'));\n\nfunc.placeholder = require('./placeholder');\nmodule.exports = func;\n","map":{"mappings":[{"source":"..\\node_modules\\lodash\\fp\\includes.js","original":{"line":1,"column":0},"generated":{"line":1,"column":0}},{"source":"..\\node_modules\\lodash\\fp\\includes.js","original":{"line":2,"column":0},"generated":{"line":2,"column":0}},{"source":"..\\node_modules\\lodash\\fp\\includes.js","original":{"line":3,"column":0},"generated":{"line":3,"column":0}},{"source":"..\\node_modules\\lodash\\fp\\includes.js","original":{"line":4,"column":0},"generated":{"line":4,"column":0}},{"source":"..\\node_modules\\lodash\\fp\\includes.js","original":{"line":5,"column":0},"generated":{"line":5,"column":0}},{"source":"..\\node_modules\\lodash\\fp\\includes.js","original":{"line":6,"column":0},"generated":{"line":6,"column":0}}],"sources":{"..\\node_modules\\lodash\\fp\\includes.js":"var convert = require('./convert'),\n    func = convert('includes', require('../includes'));\n\nfunc.placeholder = require('./placeholder');\nmodule.exports = func;\n"},"lineCount":6}},"hash":"343619c8db4b3f5296155137c0ad9641","cacheData":{"env":{}}}